hello.py
helloworld_ngealy-0.0.1.dist-info/METADATA
helloworld_ngealy-0.0.1.dist-info/WHEEL
helloworld_ngealy-0.0.1.dist-info/top_level.txt
helloworld_ngealy-0.0.1.dist-info/RECORD
